[
    {
        "Id": 11,
        "N": "Land_Wreck_Lada_Red",
        "P": [
            13459,
            284.893,
            4951.88
        ],
        "R": 13.8912
    },
    {
        "Id": 11,
        "N": "Land_Wreck_Lada_Green",
        "P": [
            13459.4,
            284.994,
            4942.43
        ],
        "R": 13.8912
    },
    {
        "Id": 11,
        "N": "Land_Wreck_V3S",
        "P": [
            13457.5,
            285.886,
            4948.44
        ],
        "R": 23.6385
    },
    {
        "Id": 11,
        "N": "Land_Wreck_Ikarus",
        "P": [
            13463.7,
            285.808,
            4943.65
        ],
        "R": 35.333
    },
    {
        "Id": 11,
        "N": "Hatchback_02_Blue",
        "P": [
            13464.4,
            284.185,
            4930.75
        ],
        "R": 13.9975
    },
    {
        "Id": 8,
        "N": "Land_Wreck_Lada_Red",
        "P": [
            5735.46,
            186.216,
            9621.65
        ],
        "R": 14.5858
    },
    {
        "Id": 7,
        "N": "OffroadHatchback_Blue",
        "P": [
            1244.52,
            331.258,
            10715.9
        ],
        "R": 13.5625
    },
    {
        "Id": 7,
        "N": "Land_Wreck_Ikarus",
        "P": [
            1232.55,
            332.768,
            10711.8
        ],
        "R": 35.333
    },
    {
        "Id": 7,
        "N": "Land_Wreck_V3S",
        "P": [
            1229.49,
            333.153,
            10704.4
        ],
        "R": 23.6385
    },
    {
        "Id": 7,
        "N": "Land_Wreck_Lada_Green",
        "P": [
            1234.69,
            331.55,
            10708
        ],
        "R": 14.8688
    },
    {
        "Id": 7,
        "N": "Land_Wreck_Lada_Red",
        "P": [
            1225.68,
            332.856,
            10705.1
        ],
        "R": 14.8688
    },
    {
        "Id": 9,
        "N": "CivilianSedan_Black",
        "P": [
            6599.66,
            381.43,
            3902.19
        ],
        "R": 16.1864
    },
    {
        "Id": 9,
        "N": "Land_Wreck_Ikarus",
        "P": [
            6587.31,
            385.316,
            3899.35
        ],
        "R": 35.333
    },
    {
        "Id": 9,
        "N": "Land_Wreck_V3S",
        "P": [
            6583.73,
            386.448,
            3892.45
        ],
        "R": 23.6385
    },
    {
        "Id": 9,
        "N": "Land_Wreck_Lada_Green",
        "P": [
            6589.16,
            384.52,
            3895.37
        ],
        "R": 16.0992
    },
    {
        "Id": 9,
        "N": "Land_Wreck_Lada_Red",
        "P": [
            6579.94,
            386.044,
            3893.25
        ],
        "R": 16.0992
    },
    {
        "Id": 10,
        "N": "Hatchback_02_Blue",
        "P": [
            4703.7,
            344.903,
            4256.11
        ],
        "R": 13.9975
    },
    {
        "Id": 10,
        "N": "Land_Wreck_Ikarus",
        "P": [
            4710.88,
            348.217,
            4245.61
        ],
        "R": 35.333
    },
    {
        "Id": 10,
        "N": "Land_Wreck_V3S",
        "P": [
            4718.59,
            348.15,
            4244.59
        ],
        "R": 23.6385
    },
    {
        "Id": 10,
        "N": "Land_Wreck_Lada_Green",
        "P": [
            4713.89,
            346.673,
            4248.63
        ],
        "R": 13.7164
    },
    {
        "Id": 10,
        "N": "Land_Wreck_Lada_Red",
        "P": [
            4719.02,
            348.373,
            4240.77
        ],
        "R": 13.8912
    },
    {
        "Id": 8,
        "N": "Land_Wreck_Lada_Green",
        "P": [
            5730.43,
            185.871,
            9613.67
        ],
        "R": 14.5858
    },
    {
        "Id": 8,
        "N": "Land_Wreck_V3S",
        "P": [
            5732.25,
            186.962,
            9619.65
        ],
        "R": 23.6385
    },
    {
        "Id": 8,
        "N": "Land_Wreck_Ikarus",
        "P": [
            5734.53,
            186.845,
            9612.23
        ],
        "R": 35.333
    },
    {
        "Id": 8,
        "N": "OffroadHatchback_Blue",
        "P": [
            5727.84,
            184.765,
            9601.26
        ],
        "R": 13.5625
    },
    {
        "Id": 16,
        "N": "Wreck_Mi8",
        "P": [
            4140.74,
            213.927,
            7930.29
        ],
        "R": 62.3211
    },
    {
        "Id": 16,
        "N": "Wreck_UH1Y",
        "P": [
            4129.23,
            213.685,
            7949.97
        ],
        "R": 55.7816
    },
    {
        "Id": 6,
        "N": "CivilianSedan_Black",
        "P": [
            1914.44,
            319.099,
            11436.2
        ],
        "R": 16.1864
    },
    {
        "Id": 6,
        "N": "Land_Wreck_Ikarus",
        "P": [
            1921.23,
            319.544,
            11425.1
        ],
        "R": 35.333
    },
    {
        "Id": 6,
        "N": "Land_Wreck_V3S",
        "P": [
            1928.88,
            321.072,
            11423.9
        ],
        "R": 23.6385
    },
    {
        "Id": 6,
        "N": "Land_Wreck_Lada_Green",
        "P": [
            1924.42,
            320.14,
            11428.4
        ],
        "R": 13.8912
    },
    {
        "Id": 6,
        "N": "Land_Wreck_Lada_Red",
        "P": [
            1929.53,
            319.477,
            11420.4
        ],
        "R": 13.8912
    },
    {
        "Id": 16,
        "N": "hardigg_Mung",
        "P": [
            4134.53,
            212.15,
            7945.02
        ],
        "R": 5.73488
    }
]